<?xml version="1.0" encoding="UTF-8"?>
<text>
	<title>TELEGRAMMEN. (REUTER&apos;S OFFICE.)</title>
	<p>NEW-YORK, 2 Aug. Slotkoersen: Goud-agio 40V+; Wissel op Londen in goud 110; 6 pCt. Amerika 1882 1121/8; lUinois 1183/4; Erie-spoorwee 75&apos;/i; Katoen middl. 28. Petroleum Standard white te Philadelphia 321/2.</p>
	<p>BERLIJN, 3 Aug. Eerstr heden avond begeeft de Heer von Bismarck zich naar Éms, vanwaar hij des avonds van den 6den e. k. wordt terug verwacht. Gedurende de dagen, welke de Heer v. Bismarck te Ems zal doorbrengen, zal ook de Heer von der Goltz, ambassadeur bij het Fransche hof, aldaar vertoeven. Volgens de Neue Prcuss. Zeitung zal heden de laatste zitting door de Hanoversche notabelen worden gehouden. Te oordcelen naar de Uitdrukkingen van sommigen hunner, zijn zij zeer tevreden met den loop der onderhandelingen met het ministerie gevoerd. Heden middag zal de ministerraad bijeenkomen. De Staats-Jnzeiger deelt in zijn heden verschenen nommer mede, dat het berigt der Nordd. Zeitung, volgens hetwelk de Heer von Savigny geen deel kan nemen aan de beraadslagingen van den Bondsraad, uithoofde van verschil van meening met andere leden van den Bondsraad, ten eenenmale onjuist is. Professer August vonßöckh, is heden in 83jarigen ouderdom alhier overleden. De prins van Hohenz ollern is gisteren te Ems aangekomen MUNCHEN, 3 Aug. De Fransche regering heeft met getracht de toetreding van Beijeren tot het nieuwe tolverbond tegen te gaan maar heeft alleen zgn ongenoegen &apos;deswege betuigd in eene depêche aan den Franschen gezant alhier, die daarvan aan den prins van B .«nzollern kennis heeft gegeven. _&quot;&apos;&apos;&apos;&apos;¦-* . PARIJS, 3 Aug. De Patrie gelooft dot de reis van den Keizer en de neuerin naar Salzbnrg uitgesteld is tot na deu Isden Augustus. De Heer Rouher vertrekt Maandag naar Karlsbad, en zal or hoogstens 25 dagen vertoeven. Eenige ministers hekben reeds een begin gemaakt met de samenstelling der begrooting voor 19G9.</p>
	<p>tOITOI., 3 Ang. Tffi. Oct-Dec 4S. ~ Whh Donskoi ffeec, 9 a 12 p. LIVERPOOL, 3 Aug. Katoen stiller. Omzet heden 8000 b.</p>
	<p>LONDEN, 3 Aug. (Slotkoersen). 3 pCt. Geconsolid. 941/ g; 5 pCt. Braz. 1865 —; 1 pCt. Ecuador —; 5 pCt. Grieken 13; Dito Coup. —; 3 pCt. Mei. 15t/4; Dito 1864 —; Afgest. N. Gren. —; 2 pCt, Dito -; Dito Uitg. —, N. Gren. Landw.£-.-; 3pCt.Port. 1853 39; 3 pCt. Dito 1856/63 ; 4V» pCt, Rnsl. 1860 —; 3 pCt. Dito 1859 —; s pCt. Dito 1862 861/2; Dito 1864 —;3 pCt. Spanje —; Vk pCt Dito 311/3; Dito Amortisablo 211/*; Dito Cert. Coup.—; 5 pCt. Turk. S. 305/ s; 3 pCt. Venez. —; 6 pCt. Dito 1862 ; 6 pCt. Dito 1864 —; U/j pCt. Dito ; 2Vj pCt. Nederl. Cert. —; 4 pCt. Dito ; Rijusp. Actiën —; 6 pCt. Amerik. 1882 727/8; Dito 1835 713/4; Obl. 7 pCt. niinois—; Actiën Illinois ; 8 pCt. Deb. Atl. &amp; Ur. West. Spw. (£ 100) 26 a —; 5 pCt. Italie —; N. Russ. Leening — a — pCt. premie; 7 pCt. Atlant. (gecons.) — a—; Deb. 22.</p>
	<p>WEENEN, 3 Aug. (Slotkoersen.) SpCt. Meta1.57.30; 5 pCt. Nat. 67.90; 5 pCt. Met. Zilv. 1864 76.—, Aand. 1854 74.50; Dito Credit Inst. 1858 124.50; Dito 1860 86 30; Dito 1864 77.70; Actiën Cred. Inst. 181.—; Dito Lemb. Czern. Spoorw. 172 50; Dito Nat. Bank 701.— ; Staats-Spoorw. Act. 229 20; Dito Noorder-Spoorweg 166 50; Dito Nieuwe Lomb. 185.25; Eng. Oost. Bank 106.25. — Wissel Londen 127 20; Hamb. 94.20; Parij? 50.45. PARIJS, 3 Aug. 3 pCt. Rente (opening) 68.97 .; 3 pCt.|Dito slotkoersen 69.071/. 4Vt pCt. Dito —; Credit Mobilair 328; Dito Fonc. ; Noord Spw. Actiën —; Dito Fr.-Oost Spw. 457; Cred. Mobiel Espagnol 328: Ned. Cred. en Dep. Bank —; Maatsch. Hand. en Nijv. -; Aand. Tunis —; Mex. Obl. Gest. 100; 3 pCt. Sp. Binn. 311/ t; 2% pCt. Dito —; 5 pCt. Italie 49.05; 5 pCt. Turk. Aleem. S. 30.80; 6 p(_ Amerika 1882 82Vs- BRUSSEL, 3 Aug. 5 pCt Met. 461/2; 6 pCt Amerika 1882 745/4; 2Va pCt. België 56.60. ANTWERPEN, 3 Aug. 5 pCt. Met. 46Vs; 6 pCt. Amerika 1882 765%. gSf&quot; Bovenstaande Telegrammen zijn reeds in een gedeelte onzer vorige oplage opgenomen.</p>
	<p>ATHENE, 1 Aug. Officieel wordt gemeld, dat volgens berigten uit Candia van 28 Julg de opstandelingen zich te Sphakia staande houden. De Turken, die gebrek aan water en levensmiddelen lijden, hebben het plateau vau Askypho weder ontruimd. De provinciën Sphakia, Rethymno en Heraklion verkeeren in vollen opstand. Een Russisch en twee Fransche onder het bevel van een admiraal staande oorlogschepen zijn van Candia met 1400 vrouwen en kinderen inden Piraeus aangekomen.</p>
	<p>NEW-YORK, 2 Aug. De radicalen hebben bg de verkiezingen in Tenne6see de zege behaald. KONSTANTINOPEL, 2 Aug. Gisteren heeft eene hevige brand het onde hotel van het ministerie van financiën vernield. Een groot aantal belangrijke stukken is&apos;hierdoor vernietigd. Zeventien personen, die wegens deelneming aan de jongste zamenzwering waren gearresteerd, zijn naar het Binnenland verbannen. • KONSTANTINOPEL, 3 Aug. De Grootvizier vertrekt naar Rutschuk om den Sultan te ontmoeten. Er worden hier groote toebereidselen g»maakt voor eene luisterrijke ontvangst van den Sultan. BERLIJN, 3 Aug. Naar men verneemt, hebben de Hanoversche notabelen hunne goedkeuring verleend aan het plan om eene algemeene commissie te benoemen tot regeling van den binnenlandschen toestand van Hanover.</p>
	<p>FLORENCE, 3 Aug. De Heer Nigra heeft zich naar Venetië begeven. De Opinione acht het gerucht, dat de Heer Nlgra ab gezant te Parijs vervangen zal worden, ongegrond. De cholera neemt te Rome een weinig af, maar woedt hevig te Frosinone en in eenigo dorpen van het gebergte.</p>
</text>
