<?xml version="1.0" encoding="UTF-8"?>
<text>
	<title>HANDELSBERIGTEN.</title>
	<p>ROTTERDAM, 12 Julij. Uit de eerste hand zijn verkocht 22 v. Maryland Tabak, per Caprera.</p>
	<p>SCHIEDAM, 12 Julij. Garst: 128, 129/2 ffi Libau ƒ 172 cont., ƒ 174 6/w.; 127/2 K Pernau ƒ 177 6/w. Moutwijn ƒ8.25; Genever ƒ 13.75; Amst. Proef ƒ 15; Spoeling ƒO.BO.</p>
	<p>HAARLEM, 12 julij. Ter Kaasmarkt waren heden hier aangevoerd 147 stapels, uitmakende 14,983 stuks, waarvan verkocht werden 146 stapels, uitmakende 14,922 stuk 3, wegende 29,365 &quot;S. Hoogste prijg ƒ28.75 per 50 ffi. Ter veemarkt waren heden alhier aangevoerd 120 schapen en lammeren, 28 stuks rundvee, benevens 11 paarden en 4 varkens.</p>
	<p>DEVENTER, 12 Julij. Op de veemarkt was de aanvoer gering. De handel was zeer levendig. Niettegenstaande de geringe voorraad voeder, welke in de weide is, werden er hooge prijzen besteed. Het dragtige en neurende vee ging voor Pruisische rekening vlug van de hand. LONDEN, 11 Julij. Suiker prijshoudend. Ecne laging Cuba werd verkocht a 22.3 en eene lading van 1210 k. Havana, ex Petroneli, N°. 13% a 20.8 voor eene naburige haven. — Koffij: Van Native werden 185 v., 112$ b. gedeeltelijk verkocht, goed ord. 68 a 69 sh., enkele kavelingen mooije kwal. bedongen 70 a7l sh., Plantation stil op Vorige prijzen. — Rijst stil. — Peper gesou&apos;eneerd, 600 b Penang zijn verkocht van 2% a 3 p. — Van Cachou vonden 120 z. middel Pcgue koopers a 24.6. — Zink stil; 100 tons op levering verkocht a£ 22 per Augustus en September. — Schotsch IJzer 54.9. — Lijnolie 32.3 a 32.6. — Talk 41.6.</p>
	<p>BOMBAY, 3 Julij (per tclegr.) Katoen: Oomra wattee wordt thans betaald met r. 310.</p>
	<p>HAVANA , 22 Junij. Suiker ferm , op de basis van 7% a 8 r. voor N°. 12. — Wisselkoers op Londen 17 pCt.</p>
</text>
