<?xml version="1.0" encoding="UTF-8"?>
<text>
	<title>OPLOSSING DER PROBLEMA&apos;S.</title>
	<p>1. Wh. FBopG7,G7op(j3, Ij 3 op C 3, C 3 op C 7, B 5 op C 4. _ 2. Wit. E3opE4,E7opE 5, B 4 op D 2.</p>
	<p>Wü hebben goede oplossingen van de opgaaf ontvangen van de HH. W. A. en A. A. te Leeuwarden, G. S. &amp; J. D.B. te Dordrecht, Schoonsigt te Haarlem, C. M„ E. P., L. G., G. d. M., een Beginner alhier. De onvermelde waren met goed.</p>
	<p>In de oplossing der Opgaaf N°. 1069 staat bij den 3den zet: B 5 op H 7; dit moest natuurlijk Zijn B 5 of H 7 geeft mat. In het Problema der Zondags-Èditie van 30 Maart, had op A 4 een zwarte Pion moeten staan.</p>
</text>
