<?xml version="1.0" encoding="UTF-8"?>
<text>
	<title>TELEGRAMMEN. (REUTER&apos;S OFFICE.)</title>
	<p>LONDEN, 10 Jan. Met de mailstoombooten Damascus en City of Vork zijn berigten uit New-York aangebragt dd. 30 Dee. jl., des namiddags. Goud agio 45; wisselkoers op Londen 158%; Illinois 1321/2; 6 pCt. Amerika 1882 105% stijgend. Katoen 52; granen en meel lusteloos; petroleum 4QI/2, dito geraffineerd 62%. Volgens een alhier verspreid gerucht hebben Frankrijk, Engeland, Italië, Oostenrijk en Spanje een verbond aangegaan, strekkende om den troon van Maximiliaan te schragen. De I ransche troepen hebben Chihuahua en Piedras negras bezet. Te Vera-Cruz zijn 1200 man Fransche troepen ontscheept. Aan generaal Schoiield is geenerlei zending opgedragen.</p>
	<p>LONDEN, 10 Jan. Consols 871/4 a % Febr.; 3 pCt. Mexic. 217/8 a 22%; 3 pCt. Dito 1864¦ —, 2 pCt. Venezuela löï/3 a 16U&gt;; 6 pCt. Dito —a —; 4% pCt. Afgestemp. Grenada 13% a % 11/8 pCt. dito 7 a 7Vo; 2 pCt. N. Dito 291/2 a 301/2; 1 pCt. Ecuador 111/2 a&apos; 12&apos;/2;Illin. Spoorw. Aand. 75% a 76; 5 pCt. Griek. 131/2 a 14; 6 pCt. Binnenl. Turken 1865 41% a 417/8; 5 pCt. Brazil. 1865— a—; 6 pCt. Amer. 1882 645/8 a •%; 3 pCt. Buitenl. Spanje 42 a 43; 21/2 pCt. Dito 34i/o a 351/2; Amort. 257/8 a 26%; Coup. Bew. 13% a 13%. WEENEN, 10 Jan. Slotkoersen: 5 pCt. Metall. 62.50; SpCt.Nat. 71.25; Zilv. Met. 1864 78.50; 8.-Act.76o; Noordb.-Act. 160.—; Oost. Aand. 66.55; Loten 1854 113.75; Cred. Loten 83.50; Eng. Oost. Bank 72.— ; Cred.-Antalt 150.80; Fr. Oost.Spoorw. 173.—; Nieuwe Lomb. 178.50.— Wissel Londen 104.80; Hamburg78.30; Parijs 41.80. BERLIJN, 10 Jan. 5 pCt. Metall. 597/8 -, 5 pCt. Nat. 63i/8; Oostenr. Crediet-Actjen —; 6 pCt. Amerik. 1882 687/8. FRANKFORT, 10 Jan. 5 pCt. Nation. 61%, — ; Oostenr. Bank. Actiën 842; Dito Cred.-Actien —; Dito Aand. 1858 127%; Dito 1860 79% ,—; Dito 1864 85%; 6 pCt. Amerik. 1882 68%, —. — Wissel: Weenen 111 Vt; Dito Amst- 10°- PARIJS, lOJan. 3 pCt. Fransche 68.37; Cred.-Mob.763;Fransch- Oostenr. Spoorw. 413; Russ. Spoorw. —; 3 pCt. Binnenl. Spanje 33%; 2 pCt. Dito —, 5 pCt. Italië 62.50-, Turken 42.50. BRUSSEL, 10Pan. Metall. 581/*; Oostenr. Cred. ; Amerika 1882 671/.1.</p>
	<p>ANTWERPEN, 10 Jan. 4% pCt. Belg. 99%; 21/-* pCt. Dito 58%; 5 pCt. Met.|sB%; spCt. Nat. 61%; 3 pCt. binn. Spanje 33%; 21/4 pCt. 34; 6 pCt. Turken 39%; 6 pCG Amerik 1832 68%; Credit üuill. --; Rott. Spoorweg 248.—,</p>
</text>
