<?xml version="1.0" encoding="UTF-8"?>
<text>
	<title>BERIGTEN UIT DE LAATSTE EDITIE VAN HET VORIG NOMMER OVERGENOMEN. AMSTERDAM, Zondag 14 October.</title>
	<p>Gisteren avond gaf de Zangvpreenigtnc Kunst en Vriendschap in het locaal de Vereéniging, ter viering vnn haar aclitjnrig bestaan, eene soiree niusicale, welke uitmuntend voldeed. l»e werkende leden gaven onder leidiug van den Heer A. Berign door de juiste en gesebakeerde voorilr.igt van: lm Frühling en IVanderlied van Bertelsuunn, Zur Wamlerschnffl en das Lied von Stcinwrin. van Berlijn, tineta van Abt en ten slotte van rite Vors.cldige alle Jungferen Marscli-SUmdchen blijk vau ijverige studie en vooruitgang, zoo lat de voordragt van e!k noinnier vol geestdrift werd toegejuicht en Dat Lied von SleUwein zelfs hi* wer«l gevraagd.</p>
	<p>Vii-r solisten, de Heeren S. (dilettant zang), Kinsbergen (trombone), Seeman (clariuet), luisterden de soiree «loor hunne talenten op. Met smaak zong de eerste het air Tancredo van Rossini; als uitstekend executant deed de Heer Jaoobfl zich kennen in de Vari- . ati-n van Mayseder en Sercn-&gt;d- van Schubert; de zekere streek en virtuositeit vau oen Heer Kinsbergen bleken uit de gelukkige wijze, waarop hij eene fantaisie uit la Favonte en hei Andante Perpeiueif van Eliason ten gehoore brug! , terwijl de Heer H. J. Seeman bewondering verwierf wegens den vollen en zuiveren toon , dien liij aan zijn instrument ontlokte, en nok zijne vaardigheid lof verdiende. Aan laatstgenoemde werd, naar wij vernemen, na den afloop van het concert door de directie het eerelidiuaatschap der zangvereeniging aangeboden.</p>
	<p>ROTTERDAM. 13 Oct. Heden afgedaan 100 a 120.000 kilo Palmolie , verwacht van Quiseinbo, per President Liricoln 11/261/4 voor la. Tarwe: 126 127 if jar. Franken ƒ355 per 241H1 ft. Bogge: 123124 8? Fransche ƒ220, p.r 3350 fi?; 116, 117 ft? Petersb. ƒ JOO, per 2100 ft?. SCHIEL«AM, 13 Oct. Rogge: Verkocht 143,2 fi? Coursclie ƒ 210 6/w Garst: 12,72 fi? Libau ƒ 201 6, w.. f 202 3,m.. 12»«/2 ff dito ƒ202 6/w.; 127/2 fi? Coursclie ƒ204 6/w. — Moiitwijn ƒ 12.75; Geever f 18 25. Amst. Proef./ 19.50; Spoeling ƒO.BO.</p>
	<p>LEYDEN, 13 Oct. Boter per 1/4 vat lste kwal. ƒ 63 a 67 , dito 2de /58a62; dito per «?ƒ I 57 &quot;s a 1 .671/5 en ƒ 1 45 a 1.55. LEEUWARDEN, 12 Oct. De aanvoer van Nieuwe Tarwe was zeer onbeduidend en door goeden kooplust werd 10 a 20 cent meer besteed. 70, 72 u/Knappe / 9,10 a 9.6(). Oude 72, 73 H&apos; Knappe..&apos; 9,90 a 10.20. Roode 73, 74 f. Nieuwe 1 9.80 a 10 en dito oude ƒ 10. 60, 90. — Rogge op hoogere prijzen gehouden en daardoor met weinig handel, 70 »r Petersb./ 6.50. 73, 74 «1 Belg. /7, 20, 40. Boeweit in de zware soorten bipia niet aangeboden -en ligte onbegeerd. 65, 66 ff Fries-che Zand ƒ6, 10, 30. Winter Gaist weinig ter veil en tot iets hoogere prijzen verkocht 60, 62 IV dito 6, 75, 90 Voersoorten van 1 5,50 tot f 6 naar wigt en kwaliteit. Haver met iets mindere aanvoer en 10 a 15 cents hooger betaald; 43, 45 E Korte Voer ƒ3.50 a 3.75, 40, 42 if Lange Voer ./ 3,20,40 Koolzaad met toeden handel, best /13 a 13.25 en overige soorten vau f 12 tot 12.75 naar kw. — Lijnzaad meer gevraagd en ruim pi ij»h., best Slagzaad vun fl2 tot 13 en mindere soorten van ./ 10 tot 11.75.</p>
	<p>De aanvoer en besteede prijzen aan de veemarkt waren als volgt: Varkens: 48 vette v.in ƒ46 tot 132; 7 magere van ƒ 18 tot 28; 15 vette Biggen vin ƒ3O tot H 5; 68 magere van f 6 tot 38; Schapen : 970 vette van ƒ22 tot 60; 15 melke van ƒ 9 tot 26 ; — magere van ƒ — tot —; — Rammen van ƒ — tot — ; 55 Lamineren van ƒ 7 tot 24; — magere Hamels van ƒ — tot—; 20 Werkpaarden van ƒ2O tot 105; — V«u-lens van ƒ — tot —. Willigt&apos; markt. Tengevolge van het door den minister van binnenl. z:iken uitgevaardiglen verbod wns er gen Rundvee ter markt. Bij de marktplaats waren echter in stallen, enz nog al verscheidene Rumb-ren aangevoerd die gretig werden opgekocht ZWOLLE, 12 Oct. De markt van Tarwe en Rogge was heden wel zoo vast als de vorige, echter met geen noemenswaardige prijsverandering. Boekweit blijft door het «aanhoudende gunstige weder hare dalende beweging voortzetten eu was lieden 20 a 30 c. lager te koop. Garst prij-moudend. Haver eu Erwten zeer weinig ter markt. Aardappelen waren wel&apos;zoo gemakkelijk te koop. Boter was willig geatemd, er werd tot ƒ 26.25 voor \ vat besteed, dit artikel blijft steeds een voorname tak van han«lel uitmaken en exÏnit ert men die van hier in enorme hoeveelheden naar Engeland. )e notering was heden: Tarwe ƒ 12.25 all, Rogge ƒ7.50 a 7 Boekweit J 6.80 a 5.70. Gnrst J 6.50, Paardenboonen / 8. Aardappelen van ƒ4 tot 2.50, Boter het achtste vat ƒ 26.25, het Ned. pond f 1.35 a 1.15, Eijereii waren zeer hoog en vonden tot 70 c. de XX) stuks hooier gretig.n aftrek, de prijs was heden ƒ3.70. ANTWERPEN, 13 Oct. Kofjij z.er vast. Uit de eerste hand zijn hedeu 6.10 b. Rio, restant per Prestoe, verkoebt. — Naar Huiden was de vraag deze week iets levendiger en de prijzen hebben zich forin gesouteiieeid. Uit de hand werden 9525 stuks oiiig«-zet en in veiling heeft men «3878 stuks beschadigde verkocht. — Rijst zeer stil. Oigepelde soorten zonder voorraad: en naar gepeld was niet de minste vraag te bespeuren. — Granen.- Tarwe zeer vast, vooral nieuwe Oostzee en Deensche soorten waren heden gevraagd, doch bijha niet aangeboden; in disponiVele jarige roode soorten was eenige omzet tot fr. 33 voor Stettin . fr. 33&apos;/«2 a 335/4 voor Ueeusche en fr. 34 a 341/4 voor Oostzee; Kogge vast op vorige prijzen; vcor ml. per April en Mei heeft men betaald fr. 20.75, tot welken prgs nog koopers zijn. AALST, 13 Oct. Ter markt van heden werüen 100 zakken Hop van den nieuwen oogst aangeboden, die grif verkocht werden tot fr. IM a 178. LONInEN, 12 Oct. De stemming voor Suiker blijft lusteloos; de prijzen blijven over het algemeen 6 p. lager dan verleden week. Eene lading vau 3260 k. Havana, ei Ino N&quot;. LU/i a 12 werd tot 24.3 afgedaan. Eojjij-. Plantation ferm prysh. — Rijst stil doch vast. M.-n heeft _0«9 b. Rangoon verkocht, meest beschadigd tot 7.6 a 10.6; enkele koopen gezond werden opgehouden tot 11.3 — (achougevraagd, en 1000 z. goed jarig Pcgue werden verkocht tet 32 sh. — Tm. hooger, mooi Straits&apos;79 sh. - Schot sch IJzer 54.9. — Lijnolie 39.6 a 39.9; - Valmaiie 44 sh. — Ta/k va loco 44.6. NEW-YORK, 29 Sept Katoen bij voortduring gevraagd en wederom Ie. hooger. middling 381/2 c. — Fotasch zeer vast en met 9.50 betaald. — Kofjij met eenige vraag naar Kl»; op levering van den nieuwen oog„t worden vaste prijzen geboden. — Cacao: Van Goaquil werden 481 b. verkocht tot 17» 17% c.goud.— Terpentijnolie &quot;sa 1 c. hooger. Men heeft 700 vaatjes verkocht in entr. tot 59 a 60 c. — Hertt zeer wiilig. mooije soorten ziju 1 &apos;«• hooger-. de omzet bestond uit 4öiW vjs. ordinaire tot 3.50 a 4-, 1650 v. Stramed en Nü. 2 tot 4.25 a 6 en 12.230 v. tot 6 a 8.25 voor N&quot;. len 8 a 9.25 voor bleek. — Petroleum geraff. in ent. gevraagd voor export en naar kwal. betaald van 38«7s a 44 es. De aanvoeren te N«.vy-lork sedert 1 Jan. best««nden uit 763,733 v. tegen 404,732 v. in 1865. - Revsel flaauw. _V* vast op 121/4 a 12S;« CS. — Oranen: tarwe 3 a 5 c. hooger wegens weinig aanvoer en beperkten voorraad. Men heelt 76.1KK) bnsh. verk. tot 1.90 voor jarige Chieago. 2.43 a 2 5,1/2 voor orden prima nieuwe dito en 2.25 a 2.31 voor N. Mllwaukee club. Rogge begeerd en 10 et, hooger, N°. 1, Western 1.05 a I.oS, Canada t.25. Koet* op Amst. -iO-/4 a 41 J/4. &apos;</p>
</text>
