<?xml version="1.0" encoding="UTF-8"?>
<text>
	<title>TELEGRAMMEN. (REUTER&apos;S OFFICE.)</title>
	<p>NEW-YORK, 25 Sept. Goud agio 43%; Wisselkoers op Londen in goud 1091/2; 6 pCt. Amerika 1832 114^ Hlinois 1211/2; firie-Spoorweg 623/4; Katoen middiing 231/ s; aanvoer 6000 b. Petroleum: Standard white te_Philadelphia 32. . LONDEN, 26 Sept. Volgens den bekend gemaakten staat van de bank is de rekening-courant der schatkist vermeerderd met £ 386,255; verminderd zijn de circulatie der billetten niet £ 296,320; de voor¦raad munt en muntmateriaal met £ 50,604-, de portefeuille met £94,568; de rekening-courant van particulieren met £ 246,630. LONDEN , 26 Sept. Het verhoor der gevangen genomen Fenians, 42 in getal, is heden begonnen. De gevangenen werden van de gevangenis naar de regtszaal begeleid door eene aanzienlijke krijgsmagt. Eene tallooze menigte was op de been. BERLIJN, 26 Sept. De N. Pr. Zeitung meldt dat de Kroonprins zich morgen over Leipzig en Neurenberg naar het eiland Mainau begeeft. Later zal hij den Koning naar Hohenzollern vergezellen. Den 9den Oct. vertrekt hij met de Kroonprinses naar Engeland. Zij zullen derwaarts door hunne jongste kinderen worden vergezeld. PARIJS, 26 Sept. Volgens den heden openbaar gemaakten staat der bank van Frankrijk zijn vermeerderd de portefeuille met 6 millioen, de rekening der schatkist met 9/io millioen. Verminderd zijn de voorraad van munt en muntmateriaal met 15/5 millioen, de beleeningen met &apos;/, millioen, de rekening-courant van particulieren met ll4/5 millioen, de circulatie der billetten met 2/3 millioen. FLORENCE, 26 Sept. Gisteren avond heeft te Genua eene demonstratie plaats gehad ter gunste der in vrijheidstelling van Garibaldi; eene deputatie heeft zich naar den prefect begeven en de in vrijheidstelling verlangd. De prefect antwoordde, dat hij het verzoek aan den minister zon mededeelen. De menigte is daarop niteengegaan. Te Milaan hebben twee niet talrijke zamenschplingen plaats gehad; een der&apos; volkshoopen bood aan de gewapende magt eenigen wederstand. Te Sienna, Verona, Pistoia en Napels hebben onbeduidende demonstratien plaats gehad, de menigte ging rustig uiteen, zonder tusschenkomst der overheid. Te Florence is eene kleine zamenscholing door eenige patrouilles der nationale garde uiteengedreven. Bij al deze demonstratien heeft men geen ongelukken te betreuren.</p>
	<p>LONDEN, 26 Sept. Thee stil. — Koffij met veel aanvoer vast. — Suiker meer gevraagd tot gesouteneerde prijzen. — Rijst goed begeerd en gestemd tot rijzing. — Talk in loco 43.9; Oct.—Dec. 43.9. Engelsche Tin ferm; Straits £ 2 lager. — Raapolie 37.9 a 38. — Lijnolie 37.6. Ter Veemarkt waren heden aangevoerd 1090 Runderen, 7160 Schapen en Lammeren, 343 Kalveren, — Varkens. De prijzen waren: Beste Kunderen 5, Schapen en Lammeren 5, Kalverens.6, Varkens 4.2. HULL, 26 Sept. Lijnolie 37.6. LIVEEPOOL, 26 Sept. Van Katoen werden 10,000 b. verhandeld tot ongeregelde, doch flaauwe prijzen.</p>
	<p>LONDEN , 26 Sept. (Slotkoersen). 3 pCt. Gecons. 941/2; 5 pCt. Braz. 1865 743/4; 1 pCt. Ecuador —; 5 pCt. Grieken ; Dito Coup. —; 3 pCt. Mei. 13%; Dito 1864 —-, Afgost. N. Gren. ; 2 pCt. Dito —; Dito Uitg. —; N. Gren. _aivaw. £—; 3 pCt. Port. 1853 —-, 3 pCt. Dito 1856/63 ; 4,&apos;/. pCt. Rusl. 1860 ; 3 pCt. Dito 1859 52; spCt.Dito 1862 87%- Dith 1864 ; 3 pCt. Spanje —-, 23/4 pCt, Dito 301/2; Dito Amortis. _f%; Dito Cert. Coup.&quot; ; 5 pCt. Turk. S. S2Vs; 3 pCt Venez. ; 6 pCt. Dito 1362 —; 6 pCt. Dito 1864 17%; 1% pCt. Dito —; 2% pCt. Nederl. Cert, ; 4 pCt. Dito ; Rijnsp. Actiën —; 6 pCt. Amerik. 1882 72%; Dito 1885 ; Obl. 7 pCt. Hlinois —; Actiën Hlinois —; 8 pCt. Deb. Atl. &amp; Gr. West. Spw. (£ 100) — a —-, 5 pCt. Italie ; N. Kuss. Leening — a — pCt. -premie ; 7 pCt. Atlant. (gecons.) 22% a—; Deb. —.</p>
	<p>Fijn Zilver 60% a 6ft% d. per once. Het stoomschip Allemani is van New-York gearriveerd. WEENEN, 26 Sept. (Slotfcoersen.) ö pOt, Meial. 55.90, SpCt.Nat 65.10; 5 pCt. Met. Zilv. 1864 73.—; Aand. 1854 71.25, Dito Credit lust. 1858 127- — ; Dito 1860 82 40; Dito 1864 73.40, Actiën Cred. Inst. 179.30; Dito Lemb. Czern. Spoorw. 172 50, Dito Nat, Bank 683.— ; Staats-Spoorw. Act. 236.—; DiteNoordër-Spoorweg 169 — ; Dito Nieuwe Lomb. 183.75; Eng. &quot;Oost. Bank 105.—. —Wissel Londen 124 15; Hamb. 91.50; Panjs 49 25. PARIJS, 26 Sept. 3 pCt. Kente (opening) 69.07%; 3 p-&gt;t. lJite slotkoersen&apos; 69.20 l 4% pCt, Dito -; Gredit Mobilair 177; Dito Fono. ___. Noord Spw. Actiën -; Dito Fr.-Oost. Spw. 481; Cred. Mobil. Espagnol 180; Ned. Cred. en Dep. Bank -; Maatscb. Hand. en ü(n. —, Aand. Tunis --, Mex. OH. Gest. 96; 3 pU. Sp Binn. 301/4; 2% PCt. Dito -; 5 pOt. Ital.e 48 80- 5 t&gt;Ct, Turk. Algem. „ 32.20; . pOt. Amerika 1882 828/4; Nieuwe Russen 309 —• Wissel: Petersb. 3/m. —; Londen kort 25.19; Amst. 3/m. 210; Hamburg 3/m. 1851/4. BRUSSEL, 26 Sept. 5 pCt. Met. 46%; 6 pCt. Amerika 1882 74%-, 31/3 vCt. België 56.50» — Wissel: Amst. köit —; Londen —,</p>
	<p>ANTWERPEN, 26 Sept. 5 nCt. Met. 46V_-, 6 pCt. Amerika 18S2 757/8. Wissel: Amst. —.—; Londen —.—. jg_§p* Bovenstaande Telegramaen zijn reeds in eer, gedeeltes onz«r vorige oplage opgeno .en.</p>
	<p>PESTH, 26 Sept. De werkkring van de Hongaarsche Boden Credit- Anstalt is ook tot Croatie en Slavonie uitgebreid. Deak wordt Zaturdag verwacht. FLORENCE, 26 Sept. (des Avonds). Tot op dit oogenblik heeft geene nieuwe demonstratie plaats gehad. In een brief aan den burgemeester van Florence betuigt de Heer Rattazzi dank aan de nationale garde voor de gisteren bewezen diensten. Volgens eene depêche uit Messina is de Heer Natoli overleden.</p>
	<p>LONDEN, 27 Sept. Het Nederlandsche oorlogs-stoomschip de Valk is van Woolwich naar Portsmouth gestoomd, ten einde de Koningin der Nederlanden af te wachten. H. M. zal zich op 1 Oct. aan boord van dat vaartuig begeven. LONDEN, 27 Sept. De mailstoomboot Douro is uit West-Indio - aangekomen, aan boord bevinden zich 109 militairen, vroeger behoord hebbende tot het leg.r van Keizer Maximiliaan. Het schip brengt tevens 2,649,879 doll. aan. Uit Chili wordt berigt, dat de vrees voor een oorlog met Spanje aldaar vermindert. Het Congres heeft het voorstel aangenomen, om een gezant van den hoogsten rang naar Mexico te zenden. De beraadslagingen over de voorstellen tot wijziging der constitntien worden voortgezet. De minister van oorlog heeft een voorstel ingediend, strekkende, om de forten welke Valparaiso omringen, te versterken; het leger is op den voet van vrede gebragt. In Peru is een nieuw complot ontdekt; de zaamgezworenen hadden het plan beraamd om den president Prado van het leven te berooven. De hoofden der zamenzwering zijn gearresteerd. Er heeft hierop eene geheime zitting van het congres plaats gehad. Naar het gevoelen der vreemde gezanten in Peru zal Spanje de vijandelijkheden niet hernieuwen. Bogota en Macquiera worden nog gevangen gehouden. PETERSBURG, 27 Sept. Üit Konstantinopel wordt het volgende gemeld: Vóór Prins Ignatieff, gezant bij de Porte, andermaal naar Livadia, alwaar de Keizer zich bevindt, zou vertrekken, gaf de Sultan hem-te kennen, dat hij in aanmerking nemende de openbare opinie in Turkije, in de Candiasche kwestie niets anders kon doen dan uitbreiding geven aan de regten der Christenbevolking op .dat eiland en elders in Turkije gevestigd. Alhier is aangekomen Mohammed Farrista, gezant van den Khan van Rokhara, ten einde bescherming van den Sultan tegen Rusland in te roepen. De Sultan heeft afwijzend hierop geantwoord.</p>
	<p>SCHIEDAM, 27 Sept. Moutwijn ƒ 15S/4. HAMBURG, 27 Sept. Granen op tijd tot 2 thal. hooger; Raapolie 24. Het weder is bijzonder fraai. PARIJS , 27 Sept. Raapolie disponibel en per Sept. fr. 99.—, dito per 3 laatste maanden fr. 99.50; 4 eerste maanden van 1868 fr. 99.50. — Voorloop disponibel en per Sept. in entr. fr. 67.50-, 2 laatste maanden fr. 63.50. — Lijnolie disponibel en per Sept. fr. 105.50; dito per 3 laatste maanden fr. 102.—. — Meel, 6 merken disponibel en per Sept. fr. 86. —-, dito per Oct. 84.— ; dito per 2 laatste maanden fr. 81.50; dito stand. Parijs disponibel en per Sept. fr. 52.— ; dito per 3 laatste maanden fr. 50.50. — Beetwortelsuiker, inlandsch goede 4de soort N°. 12 disponibel en per Sept. 58 a 59. ANTWERPEN, 27 Sept. Petroleum, dispon, white, gold £r. 54i_.</p>
	<p>LONDEN, 27 Sept. 3 pCt. Consols 94% a —; 3 pCt. Meiicanen 151/4 a i_-, Dito 1864 —; 2 pCt. Venez. —; 6 pCt. Dito 1862 —; 48/4 pCt. Gren. afg. a—; 1% pCt. Dito — a —; 2 pCt. Nieuwe Dito —, 1 pCt.Ecuador a ; HlinoisSpoorw.-Aandeelen 761/2 a 771/.; 5 pCt. Grieken 13V. a 14-, 5 pCt. Binnenl. Turken 1865 32 a 1/4; 5 pCt. Braz. 1865 —; 6pCt. Amerika 1882 72% a a 7/g; 3, pCt. Buitenl. Spanje —a — ; 2% pCt. Dito — a —; Amort. 191/4 a 1/2; Coup. Bewijz. —— a—-, 5 pCt. Italie 431/3 a 3/4; Euss. Leening— pCt. premie; 7 pCt.AtL22I/3 a 231/2; Debent. 25a27; Amerika 1885 — a -. Voor het Grenada-dividend is £ 1353 aangebragt. BEKLIJN, 27 Sept. (Slotkoersen.) 5 pCt. Met. 46; spCt. Naiion. 53; Oostenr. Aand. 1860 667/8; 5 pCt. Italie 48i/8; Lomb. Shares 99V2; 5 pCt. Kuss. 1822 85%, Dito 1862 86; Aand. 1864 IOOVj ; Dito 1886 94%, 41/2 Pruisen Oblig. 97% 6 pGt. Amorika 1882 76%-, Holl. Spoorweg-Act. 104. Wissel: Londen 3/m6.233/4; Parijs 2/m.80&quot;/i2-, Hambnrg2&apos;m. 150; Amst. 2/m. 1421/4; Dito kort 14275; Weenen 2/m. 807/8; Petersb. 3/m. 918/ g. FEANKFORT, 27 Sept. (Slotkoersen). 5 pCt. Metall. 1866 46%; Dito Nat. 513/4-, Oost. Aand. 1860 667/8; Dito 1864 70%; Metall. 1859 58% 6 pCt. Amerika 1882 75U/i6; Dito per uit.—; Dito 1885 73%.— Wissel: Londen k. z. 1191,.; Weenen k. z. 95%; Amst. k.z. 100. HAMBURG, 27 Sept. 5 pCt. Russ. 1862 82; Oost. Aand. 1860 66V.; 6pCt.Amerika 1882 691/4. — Wissel: Londen 13.07%: Arast. 35.50; Parijs 187-, Petersb. —; Disconto is/4 pCt.; 5 pCt. Italie 471/2; Lombarden 367V2. PARIJS, 27 Sept. Fransche 3 pCt. 69.20; Credit Mobilier 177; Fransch-Oostenr. Spoorw. 480; 3 pCt. Binnenl. Spanje 30Vs; 2% pCt. Dito —-, 5 pCt. Italie 48.80, 5 pCt. Turken 32.25; Mexic. Loten —; 6 pCt. Amerika 1882 82%; Nieuwe Russen 309.25. CUXHAVEN, 27 Sept. Uitgezeild: Willem I, S., Amst.</p>
</text>
