<?xml version="1.0" encoding="UTF-8"?>
<text>
	<title>HANDELSBERIGTEN.</title>
	<p>AMSTERDAM, Donderdag 27 April.</p>
	<p>Door de N. H. M. zyn 72,200 kranj. Java Suiker tegen 23 Mei in veiling aangeslagen. _^</p>
	<p>Dc gisteren door do N. H. M. te Rotterdam gehouden veiling van 15,203/4, 34/8 en 1668/12 k. JAVA THEE, is afgeloopen als voigt: Kisten. Verkocht. Boei 625/4 50 a 87 c Congo Boei 163/4 ~. 61 n 81 n Con|o 5017/4 4/8 213/12 70 0 110 // Pecco Congo ...... 101 // — // Kempoei I°s/4 96 n 100 // Pecco Kempoei 18/4 86/12 115 it 123 // Souchon 4519/4 251/12 76 0 129 // Pecco Souchon 109/4 _ 114 , 124 0 Pecco 1538/4 . 495/12 87 0 291 0 Schin 229/4 33 „ g 3 „ Thunkay 1707/4 45 „ 104 0 Hysant 1091/4 . 56  126 &apos;0 Uxim 2/4 407/12 67 0 120 0 Joosjes (G. B.) 27/8 167/12 102 // 150 0 Joosjes (F. B.) 3/8 49/12 25 0 144 // Opgehouden in de veiling van 20 April en 12 October 1864 : 59/4 kisten Congo Boei 51 a 55 e. 51/4 « Congo 70 0 —11 69/4 * Souchon. ....... 88 // 88 0 58/4 0 Pouchon 67 0 74 0 206/4 0 Pecco 110 0 118 0 30/12 * Pecco Kempoei . . , , 118 „ 125 // Alles Y«tloeht.</p>
	<p>SCHIEDAM, 26 April. Moutwijn ƒ10.25; Jenever ƒ 15.73; &amp;**&apos; Proef ƒ 17; Spoeling ƒ0.60. &apos; __ HAARLEM, 26 April. Ter Kaasmarkt zijn heden hier *&lt;H&gt;6eT°v. 28 stapels Kaas, uitmakende 2420 stuks; verkocht werden 26 ***?$ uitmakende 2230 stuks, wegende 4355 ffi. Hoogste prijs ƒM&apos; per 50 ffi. - n„,l ZWOLLE, 26 April. Op de groote jaarmarkt, die gisteren te M% gehouden werd, is het Rundvee tot ongekend hooge prijzen ver*c.°^e([ zoo als de oudste kooplieden zich niet herinneren. Door buitenl. koopu* werden de dragtige Koeijen met ƒ 180 a 225 betaald en voor guste dio in het najaar bij raming 350 ffi zullen wegen besteedde men J i&apos;__ ƒlBO, de zwaardere soorten naar evenredigheid. Al wat gekocht&quot;^ is met den meesten spoed vervoerd, zoodat dezen ochtend wel 25 o wagens van den centraal-spoorweg met Koeijen volgestopt ziju, y Rotterdam gedirigeerd wolden, van waar zy naar het buitenland zonden worden. . w DEVENTER, 26 April. Op de veemarkt waren 172 koeijen en sß^ 28 paarden aan de lijn. In de prijzen was geene verandering sedert vorige week. De handel was zeer levendig. — De aanvoer van linnen was heden gering. Wegens do steeds lende prijzen van de katoen was de handel zeer gedrukt. Men bestee van 25 tot 35 e. per el. , RAALTE, 26 April. Boter ƒ 19 a 21.— per % vat, ƒ 9-°^, 10.25 per i/fe vat; Rogge ƒ 5.90 a 6.10; Boekweit ƒ 5.80 a 6; B? , ƒ3.40 a 3.60; Garst ƒ 5.— a 5.30, alles per mud, gemoste Var l 44 a 46 c. per ffi; jarige dito ƒ32 a 40; oude Biggen ƒ 16 a 18; &amp; dito ƒ 7.50 a 9; dragtige Koeijen ƒ 120 a 140; guste dito fss_fZ\ gerookt Spek 30 e. de 5 ons; gerookte Hammen 26 a 28 e. de 5 ° Eijeren ƒ 2.15 dc 100 stuks. m OMMEN, 26 April. Op de gisteren alhier gehouden Paaschvcefl»^ wa 3 de handel in koeijen en schapen vrij levendig, alles ging tot verhoogde prijzen vlug van do hand. Boter por % vat ƒ2O » Kippen-Eijeren per 100 st. ƒ 2; Boekweit en Rogge tot vorige P^U DEDEMSVAART , 26 April. De marktprijzen waren heden als r»&apos;, Rogge ƒ 5.50 a 5.80; Boekweit ƒ 5.65 a 6 10; Aardappelen ƒ l;&quot;^ 2.10; Boter 70 a 80 c. per ffi; Kip Eijeren ƒ 1.90; Eenden-E&apos;/ ƒ 2.60 beide per 100 stuks. LAND VAN ALTENA, 26 April. In de laatste dagen is me% artikelen wederom verandering en heden is het als volgt: AardspP ,(t 20 a 30 c. hooger ƒ2.10 a 2.40; Appelen hooger ƒ 1.70 a2-I^^!. 10 c. lager ƒ 0.85 per ffi; Eijeren vorigen prijs.. 2.60 per I°**^ (beide laatsten voor 8 dagen vastgesteld); vette Varkens onver» , 18 a 18% c. vuil; Hooi iets lager/-17.50 a 18; Stroo lager ƒ»■ 10.25; Vlas met vraag en meer handel. BREDA, 26 April. Op do heden binnen de gemeente Leurg&lt;* .^.r voorjaars-, paarden- en beestenmarkt wa 3 nog al veel te doem 1/ Li del in jong vee, meestal weibeesten, was vrij levendig. Niet mii&apos;Oe p 200 stuks was er aangevoerd, en voor goede prijzen veel verkoel1 • paarden was de handel algemeen stil. rhet FRANKFORT, 21 April. Huiden: De afloop van do veiling was ov^ geheel weinig voldoende en de prijzen waren flaauw. De voor j, der geschikte zware Huiden van goede kwal. daalden 2 a 3 th. p en de ord. 5 th. ml. Huiden voor Zoolleder werden ook iets lage .j( on wel van 4 a 5 th. per qql. Praaije Koehuiden zijn weinig ge maar de ord. 3 a 4 th. Ossenhuiden en Kalfsvellen waren vee geboden en daalden 5 a 6 sh. vergeleken bij de najaarsmis- &quot;[. $&gt; taalde voor zware Hniden voor iisoïleder 50 a 60 ffi goede kwal- p-^ 63; fraaije kwal. iets ligter th. 48 a 54, ord. 42 a 46 ;inl. Huid&quot; £U Zolleder, zware th. 50 a 55, ligte 45 a 49, Koe- 42 a 53 naaf - Ossen- 48 a 62 en Kalfsvellen 86 a 124 naar kwal. J_,f LONDEN, 25 April. Suiker was heden wederom meer ge^SF de prijzen zijn 1 sh. hooger dan verleden Vrijdag; tot deze Vr&quot;&apos; te tering vond bijna al hetgeen in veiling werd aangeboden koope &gt; yj.l wijl bovendien belangrijke afdoeningen uit de hand plaats had&lt; &apos;_\t^&apos; W.-Ind. werden iv het geheel 2660 v. verkocht. Op levering W* eene lading Portorico a 23 sh. afgedaan. Geraffineerde Suiker ff digo vraag en ruim 1 sh. hooger dan Vrijdag. — KofJ&apos;J: ft. Ceylon 6 p. hooger, goed ordinaire 68 a 69 sh., Plant»»^ £__,&lt;&gt;&lt; en gestemd tot rijzing. — Thee vast en met goede vraag- &quot;. &apos;i ferm prijsh., men heeft 49 b. Surinaamsch goed en moo&apos;rJ2i&gt; b. $» a 75 6 verkocht. — Rijst vaster. Uit de hand werden 19&apos;&quot;rLr&apos;gte«* goon afgedaan a 10 sh. en 10,000 b. Bassein tot 9 a 9.3. — -TV&quot; giiif gevraagd, ca. 5000 b. Penang vonden koopers tot 3% a3_ pore tot 3% a 3«, p. — Van Cachou werden 944 b. meest fp van 24.6 a 25.6. &apos;— Schotsch IJzer 55.9. — Lijnolie 31-9--stil op 41.3. , _.en *5 BALTIMORE, 8 &apos;April. Wubal. Er ging in de afetlo^^ niets om en cic noteringen zijn zoo goed als nominaal, 1 &apos;I, bedroeg 245 v. Maryland, 60 v. Ohio en 4v. Virginie. &quot;,&amp;eft, naar Rotterdam 1441 v. De voorraad, zoo aan boord als l 0 qWL huizen, bedraagt 15,802 v. — QuercUron zonder vraag, nor- trols&quot; 407 z. werden naar Rotterdam uitgeklaard. Vrachten flaauw. * \\. f naar Liverpool 6 sh. Wissel op Londen 108 a 109 J. Amsterö» SAMARANG, 10 Maart. Kof Jij: Eenige partijen werden W $_* afgedaan tot ƒ4O per pikol, betaalbaar bij levering. — &lt;-]4_N™-.^ vonden geen transacties op levering plaats; hooger dan voor J ___\l&apos; wordt niet meer geboden. — Indigo ƒ 4.35 p. ffi Prim9.«;ffetg,&gt; echter zeer schaarseh voorkomt, afwijkende soorten zijn slecn__ jc*^ reduciien te plaatsen. — Huiden zonder handel. — Rijst- . , __t aanvoeren van Batavia en Soerabaija gingen de prijzen W&apos; „;et bleven de noteringen onveranderd. — Cubeben kwamCD °0., r l&apos;l _ markt.— Rotting f 11a 13 naar kwal. De meerdere yrft?fß. l)&quot;^ waden heeft door de hooge rijstprijzen niet kunnen aanhoua j __**&amp;__ bleven echter geretireerd, zoodat geene afdoeningen tot s jjjsck*j_ en noteringen van ruwe en witto Calicots als nominaal mo^.^, cc&apos; worden. Drills trokken meer de attentie der koopers tot jj,eo»_^ partijtjes in publieke vendutio gebragt, vonden tot vorig 6 rvr33iCJ- j pers. Geverwde Katoenen onverkoopbaar. Jaconcts weinig fc j vo01&quot;^ Boter overvoerd, prijzen onveranderd. — Hammen vaet j 0 en weinig gevraa;;d. — Kaas onveranderd. — Vracht zwaar goed. — Wisselkoers 104 pCt. om*o &lt;r &quot; MANILLA, 6 Maart. Tabak zonder belangrijken gottet&gt;^s het oogenblik valt er aan gcone verbetering van &lt;* g(. r»9?)&apos; tt verlaging van de prijzen te denken. — Sigaren re del &apos;J -:2Cn % y,_nr Suiker: Visayas bragt 3 a 3.25 doll. op; tot die P •».„ vet j). evenwel niet veel omgaan, daar dio veel te hoog zJj ft T-^cor ding tot de noteringen te London ; raff. soorten bragten 4- ,p V° pur&quot; op naar kwal. — Hennep vast. a 5 doll. is niet grif te f..op** rante kwal.; overige soorten doll. 5.25 a 6.25 c. ____ jjljil&apos;;(J_ &apos; pers voor Frankrijk; 6000 pie. bedongen doll. 14-62 c&apos; _,_._ *- t\4&apos; berigten uit China zijn de prijzen alliier 12 a2oo. &apos;. f^^a; ,_ Ü&apos;hout regte stokken doll. 1.75. — Indigo met vf**L.&amp;»&quot;!!s•*? bragten doll. 48 a 65 naar kwal. op, en or zijn ng 2-oU&lt;].l ft dol|- sl2&apos; — Paerlmoerschelpen gevr j.agd; 500 pic. werden g gUirt&apos;^jt. &apos; verk. — Manufacturen mvt meer handel; gebl. en °^ &apos;„eb\- v a 25 c. hooger; er werden 9069 ps. gebl. en ,  Pll. Vrachten zeer flaauw, Koers op Londen 6 m. zigt *2?j,_»^ etl i , SHANGAY, 8 Maart. In zwarte Thee was niet veei __ ;o, (9, » verkocht slechts 600 kn. Oor.am a ts. 21, 143 kn. do- w kn. diverse soorten. Groene Thee met vrij levendigen a-xtO° , K a 6 luger. Men verk. 16407 halve kn. De voorra^onaBi »A &quot;ffi &apos;&quot; groot. Men noteeit Ningchovv ts. 20 a 24} ,en oa Ö,&apos;-*^. f Totale uitvoer naar Engeland 44,277,763 ffi 7-,f(,r(. Ne *» &apos; . &lt; groene, tegen 46,961,700 « zwarte en 9,105,739 &amp; b \_tl ta» yo&amp;* CANTON. 10 Maart. Thee werd wel zoo g&quot;&apos; kn. Indie, als 2 ehops Country Congo ats 21J- a 20, •&gt; &apos;aßton &lt;W Hyson tot ts. 44 a 68, eu 420 &quot;kn., en 250/2 &quot;°; de Cf V 0 oil, tii 16 a 17. Voor Engeland werd alleen de voifc j, o», __ » gekocht, als 2000 kn. Secnted Oranje Pecco tot ts. t 9. i dito Caper tot ts. 13J a 27, 4000 kn. Gwipow^ cbop« 610/2 kn. Young Hyson tot ts. 16 a \- Voorra* _olol.g eu Congo, 650/2 kisten dito Souchong, 4,500 2 ki»^1 e 3. irïjion im™ v,-„,-i,ia„ ni.tt li.-tHi- naar L^iul- . I</p>
</text>
